{
    "components" : [
        { "name" : "pieceArm",
          "type": "arm",
          "model": "ur",
          "attributes": {
              "host" : "10.237.115.65"
          }
        },
        { "name" : "cameraOver",
          "type" : "camera",
          "model" : "intel",
          "attributes" : {
              "host": "10.237.115.131",
              "port": 8181,
              "num" : "1"
          }
        },
        { "name" : "grippie",
          "type" : "gripper",
          "model" : "serial"
        },
        { "name" : "gripperCam",
          "type" : "camera",
          "model" : "intel",
          "attributes": {
              "host" : "127.0.0.1",
              "port" : 8181
          }
        }

    ]
}
