{
    "boards" : [
        { "name" : "local",
          "model" : "pi",
          "motors" : [
              { "name" : "g",
                "pins" : {
                    "a" : "11",
                    "b" : "13",
                    "pwm" : "18"
                },
                "encoder" : "encoder",
                "encoderB" : "encoder-b",
                "ticksPerRotation" : 100
              }
          ],
          "analogs" : [
              { "name" : "current",
                "pin" : "1"
              },
              { "name" : "pressure",
                "pin" : "0"
              }
          ],
          "digitalInterrupts" : [
              { "name" : "encoder",
                "pin" : "15"
              },
              { "name" : "encoder-b",
                "pin" : "16"
              }
          ]
        }
    ],
    "components" : [
        { "name" : "vg1",
		  "type": "gripper",
		  "model": "viam"
        }
	]
}
